capstone_logger/__init__.py
capstone_logger/logger.py
capstone_logger-0.0.1.dist-info/LICENSE
capstone_logger-0.0.1.dist-info/METADATA
capstone_logger-0.0.1.dist-info/WHEEL
capstone_logger-0.0.1.dist-info/top_level.txt
capstone_logger-0.0.1.dist-info/RECORD
